README.md
setup.py
pyRoControl/__init__.py
pyRoControl/_intercommunication.py
pyRoControl/command.py
pyRoControl/control.py
pyRoControl/test.py
pyRoControl.egg-info/PKG-INFO
pyRoControl.egg-info/SOURCES.txt
pyRoControl.egg-info/dependency_links.txt
pyRoControl.egg-info/top_level.txt